[
  {
    "id": "lv53-01",
    "jp": { "orth": "到着", "reading": "とうちゃく" },
    "defs": {
      "en": "arrival",
      "zh": "到达 / 抵达",
      "ko": "도착",
      "vi": "đến nơi / tới",
      "es": "llegada",
      "fr": "arrivée",
      "de": "Ankunft",
      "it": "arrivo",
      "pt": "chegada",
      "id": "kedatangan / tiba",
      "tl": "pagdating / arrival",
      "th": "การมาถึง",
      "ru": "прибытие / приезд",
      "hi": "पहुंचना / आगमन",
      "km": "ការមកដល់",
      "lo": "ການມາຮອດ",
      "ne": "पहुंच / आगमन"
    },
    "pos": "noun"
  },
  {
    "id": "lv53-02",
    "jp": { "orth": "出発", "reading": "しゅっぱつ" },
    "defs": {
      "en": "departure / starting",
      "zh": "出发 / 启程",
      "ko": "출발",
      "vi": "khởi hành / xuất phát",
      "es": "salida / partida",
      "fr": "départ",
      "de": "Abfahrt / Aufbruch",
      "it": "partenza",
      "pt": "partida / saída",
      "id": "keberangkatan / berangkat",
      "tl": "pag-alis / departure",
      "th": "การออกเดินทาง",
      "ru": "отправление / выезд",
      "hi": "प्रस्थान / रवाना होना",
      "km": "ការធ្វើដំណើរ / ចេញដំណើរ",
      "lo": "ອອກເດີນທາງ / ອອກໄປ",
      "ne": "प्रस्थान / यात्रा सुरु"
    },
    "pos": "noun"
  },
  {
    "id": "lv53-03",
    "jp": { "orth": "行き先", "reading": "いきさき" },
    "defs": {
      "en": "destination / whereabouts",
      "zh": "目的地 / 去向",
      "ko": "행선지 / 목적지",
      "vi": "điểm đến / nơi đến",
      "es": "destino / lugar a donde ir",
      "fr": "destination / lieu de destination",
      "de": "Zielort / Bestimmungsort",
      "it": "destinazione / meta",
      "pt": "destino / direção",
      "id": "tujuan / arah pergi",
      "tl": "patutunguhan / destination",
      "th": "จุดหมายปลายทาง / ที่ไป",
      "ru": "пункт назначения / место назначения",
      "hi": "गंतव्य / जहाँ जाना है",
      "km": "គោលដៅ / ទិសដៅ",
      "lo": "ຈຸດໝາຍທາງ / ປາຍທາງ",
      "ne": "गन्तव्य / जाने ठाउँ"
    },
    "pos": "noun"
  },
  {
    "id": "lv53-04",
    "jp": { "orth": "案内", "reading": "あんない" },
    "defs": {
      "en": "guide / information / showing around",
      "zh": "指南 / 向导 / 引导",
      "ko": "안내 / 길잡이",
      "vi": "hướng dẫn / chỉ dẫn",
      "es": "guía / información / orientación",
      "fr": "guide / information / indication",
      "de": "Führung / Auskunft / Anleitung",
      "it": "guida / informazione / indicazione",
      "pt": "guia / informação / orientação",
      "id": "panduan / informasi / petunjuk",
      "tl": "patnubay / information",
      "th": "คำแนะนำ / การนำทาง",
      "ru": "информация / экскурсия / руководство",
      "hi": "मार्गदर्शन / जानकारी",
      "km": "ការណែនាំ / ព័ត៌មាន",
      "lo": "ການແນະນຳ / ຂໍ້ມູນ",
      "ne": "मार्गदर्शन / जानकारी"
    },
    "pos": "noun"
  },
  {
    "id": "lv53-05",
    "jp": { "orth": "観光", "reading": "かんこう" },
    "defs": {
      "en": "sightseeing / tourism",
      "zh": "观光 / 旅游",
      "ko": "관광",
      "vi": "tham quan / du lịch",
      "es": "turismo / visita",
      "fr": "tourisme / visite",
      "de": "Tourismus / Besichtigung",
      "it": "turismo / visita",
      "pt": "turismo / visita",
      "id": "wisata / pariwisata",
      "tl": "pamamasyal / tourism",
      "th": "การท่องเที่ยว / เที่ยวชม",
      "ru": "туризм / экскурсия",
      "hi": "पर्यटन / घूमना",
      "km": "ទេសចរណ៍ / ធ្វើដំណើរទស្សនកិច្ច",
      "lo": "ການທ່ອງທ່ຽວ",
      "ne": "पर्यटन / घुमफिर"
    },
    "pos": "noun"
  },
  {
    "id": "lv53-06",
    "jp": { "orth": "風景", "reading": "ふうけい" },
    "defs": {
      "en": "scenery / landscape / view",
      "zh": "风景 / 景色",
      "ko": "풍경 / 경치",
      "vi": "phong cảnh / quang cảnh",
      "es": "paisaje / vista / panorama",
      "fr": "paysage / vue / décor",
      "de": "Landschaft / Szenerie / Aussicht",
      "it": "paesaggio / panorama",
      "pt": "paisagem / vista",
      "id": "pemandangan / panorama",
      "tl": "tanawin / scenery",
      "th": "ทิวทัศน์ / ภูมิทัศน์",
      "ru": "пейзаж / вид / ландшафт",
      "hi": "दृश्य / परिदृश्य",
      "km": "ទេសភាព / ទេសចរណ៍",
      "lo": "ທິວທັດ / ທິວພາບ",
      "ne": "दृश्य / प्राकृतिक सौन्दर्य"
    },
    "pos": "noun"
  },
  {
    "id": "lv53-07",
    "jp": { "orth": "景観", "reading": "けいかん" },
    "defs": {
      "en": "landscape / outlook / scenery (esp. aesthetic view)",
      "zh": "景观 / 风貌",
      "ko": "경관 / 풍경",
      "vi": "cảnh quan / quang cảnh",
      "es": "paisaje / entorno visual",
      "fr": "paysage / panorama",
      "de": "Landschaft / Szenerie",
      "it": "paesaggio / panorama",
      "pt": "paisagem / cenário",
      "id": "pemandangan / lanskap",
      "tl": "tanawin / landscape",
      "th": "ภูมิทัศน์ / ทัศนียภาพ",
      "ru": "пейзаж / ландшафт",
      "hi": "परिदृश्य / दृश्यावली",
      "km": "ទេសភាព / ទេសភាពស្អាត",
      "lo": "ພູມິທັດ / ທິວທັດງາມ",
      "ne": "परिदृश्य / दृश्य सौन्दर्य"
    },
    "pos": "noun"
  },
  {
    "id": "lv53-08",
    "jp": { "orth": "旅行者", "reading": "りょこうしゃ" },
    "defs": {
      "en": "traveler / tourist",
      "zh": "旅行者 / 游客",
      "ko": "여행자 / 관광객",
      "vi": "người du lịch / khách du lịch",
      "es": "viajero / turista",
      "fr": "voyageur / touriste",
      "de": "Reisender / Tourist",
      "it": "viaggiatore / turista",
      "pt": "viajante / turista",
      "id": "pelancong / wisatawan",
      "tl": "manlalakbay / turista",
      "th": "นักท่องเที่ยว / ผู้เดินทาง",
      "ru": "путешественник / турист",
      "hi": "यात्री / पर्यटक",
      "km": "អ្នកធ្វើដំណើរ / អ្នកទេសចរ",
      "lo": "ນັກທ່ອງທ່ຽວ / ຜູ້ເດີນທາງ",
      "ne": "पर्यटक / यात्रु"
    },
    "pos": "noun"
  },
  {
    "id": "lv53-09",
    "jp": { "orth": "写生", "reading": "しゃせい" },
    "defs": {
      "en": "sketching / drawing from nature",
      "zh": "写生 / 写实",
      "ko": "사생 / 스케치",
      "vi": "vẽ phong cảnh / ký họa",
      "es": "boceto / dibujo del natural",
      "fr": "croquis / dessin d’après nature",
      "de": "Skizzieren / Naturstudie",
      "it": "schizzo / disegno dal vero",
      "pt": "esboço / desenho ao natural",
      "id": "menggambar alam / sketsa",
      "tl": "pag-guhit mula sa tanawin / sketching",
      "th": "วาดภาพจากธรรมชาติ / สเก็ตช์",
      "ru": "этюд / зарисовка с натуры",
      "hi": "चित्र बनाना / रेखांकन",
      "km": "គំនូរពីធម្មជាតិ",
      "lo": "ວາດຮູບຈາກທຳມະຊາດ",
      "ne": "प्राकृतिक चित्रकला / स्केच"
    },
    "pos": "noun"
  },
  {
    "id": "lv53-10",
    "jp": { "orth": "航空機", "reading": "こうくうき" },
    "defs": {
      "en": "aircraft / airplane",
      "zh": "航空器 / 飞机",
      "ko": "항공기 / 비행기",
      "vi": "máy bay / phương tiện hàng không",
      "es": "aeronave / avión",
      "fr": "aéronef / avion",
      "de": "Luftfahrzeug / Flugzeug",
      "it": "aeromobile / aereo",
      "pt": "aeronave / avião",
      "id": "pesawat terbang / wahana udara",
      "tl": "sasakyang panghimpapawid / eroplano",
      "th": "เครื่องบิน / ยานพาหนะทางอากาศ",
      "ru": "воздушное судно / самолёт",
      "hi": "विमान / हवाई जहाज़",
      "km": "យន្តហោះ / ឧបករណ៍ហោះហើរ",
      "lo": "ເຮືອບິນ / ຍານພາຫະນະທາງອາກາດ",
      "ne": "विमान / हवाई साधन"
    },
    "pos": "noun"
  }
]
