[
  {
    "id": "lv89-01",
    "jp": { "orth": "有給", "reading": "ゆうきゅう" },
    "defs": {
      "en": "paid leave / paid vacation",
      "zh": "带薪休假 / 有薪假期",
      "ko": "유급휴가 / 유급휴일",
      "vi": "nghỉ phép có lương / kỳ nghỉ có trả lương",
      "es": "vacaciones pagadas / permiso remunerado",
      "fr": "congé payé / vacances rémunérées",
      "de": "bezahlter Urlaub / bezahlte Freistellung",
      "it": "ferie retribuite / permesso pagato",
      "pt": "férias remuneradas / licença paga",
      "id": "cuti berbayar / libur dibayar",
      "tl": "paid leave / bayad na bakasyon",
      "th": "ลาพักร้อนแบบได้รับค่าจ้าง",
      "ru": "оплачиваемый отпуск / оплачиваемое отсутствие",
      "hi": "वेतन सहित अवकाश / पेड लीव",
      "km": "វិស្សមកាលមានប្រាក់ឈ្នួល",
      "lo": "ພັກມີເງິນເດືອນ",
      "ne": "तलबसहित बिदा"
    },
    "pos": "noun"
  },
  {
    "id": "lv89-02",
    "jp": { "orth": "締切日", "reading": "しめきりび" },
    "defs": {
      "en": "deadline / due date / closing date",
      "zh": "截止日 / 最后期限",
      "ko": "마감일 / 제출기한",
      "vi": "hạn chót / ngày nộp",
      "es": "fecha límite / plazo de entrega",
      "fr": "date limite / échéance",
      "de": "Abgabetermin / Stichtag",
      "it": "scadenza / termine ultimo",
      "pt": "prazo final / data limite",
      "id": "tanggal batas / tenggat waktu",
      "tl": "deadline / takdang petsa",
      "th": "วันครบกำหนด / วันสิ้นสุด",
      "ru": "крайний срок / дата сдачи",
      "hi": "अंतिम तिथि / समय सीमा",
      "km": "កាលបរិច្ឆេទផុតកំណត់",
      "lo": "ວັນກໍານົດສຸດທ້າຍ",
      "ne": "अन्तिम मिति / समय सीमा"
    },
    "pos": "noun"
  },
  {
    "id": "lv89-03",
    "jp": { "orth": "社内", "reading": "しゃない" },
    "defs": {
      "en": "within the company / internal / in-house",
      "zh": "公司内部 / 内部",
      "ko": "사내 / 회사 내부",
      "vi": "trong công ty / nội bộ",
      "es": "dentro de la empresa / interno",
      "fr": "au sein de l’entreprise / interne",
      "de": "innerhalb der Firma / intern",
      "it": "interno all’azienda / aziendale",
      "pt": "interno à empresa / dentro da companhia",
      "id": "dalam perusahaan / internal",
      "tl": "sa loob ng kumpanya / internal",
      "th": "ภายในบริษัท / ภายในองค์กร",
      "ru": "внутри компании / внутренний",
      "hi": "कंपनी के अंदर / आंतरिक",
      "km": "ក្នុងក្រុមហ៊ុន / ផ្ទៃក្នុង",
      "lo": "ໃນບໍລິສັດ / ພາຍໃນ",
      "ne": "कम्पनीभित्र / आन्तरिक"
    },
    "pos": "noun"
  },
  {
    "id": "lv89-04",
    "jp": { "orth": "社外", "reading": "しゃがい" },
    "defs": {
      "en": "outside the company / external",
      "zh": "公司外部 / 外部",
      "ko": "사외 / 회사 외부",
      "vi": "bên ngoài công ty / bên ngoài",
      "es": "fuera de la empresa / externo",
      "fr": "à l’extérieur de l’entreprise / externe",
      "de": "außerhalb der Firma / extern",
      "it": "esterno all’azienda / fuori dalla società",
      "pt": "fora da empresa / externo",
      "id": "luar perusahaan / eksternal",
      "tl": "labas ng kumpanya / external",
      "th": "ภายนอกบริษัท / ภายนอก",
      "ru": "вне компании / внешний",
      "hi": "कंपनी के बाहर / बाहरी",
      "km": "ក្រៅក្រុមហ៊ុន / ខាងក្រៅ",
      "lo": "ນອກບໍລິສັດ / ພາຍນອກ",
      "ne": "कम्पनीबाहिर / बाह्य"
    },
    "pos": "noun"
  },
  {
    "id": "lv89-05",
    "jp": { "orth": "担当", "reading": "たんとう" },
    "defs": {
      "en": "person in charge / responsibility / handling",
      "zh": "负责人 / 担当",
      "ko": "담당 / 책임자",
      "vi": "phụ trách / đảm nhiệm / người phụ trách",
      "es": "encargado / responsable / a cargo de",
      "fr": "responsable / en charge de",
      "de": "verantwortlich / zuständig / Betreuer",
      "it": "responsabile / incaricato",
      "pt": "responsável / encarregado",
      "id": "penanggung jawab / menangani",
      "tl": "tagapangasiwa / in charge",
      "th": "ผู้รับผิดชอบ / ดูแล",
      "ru": "ответственный / 담당 / руководитель участка",
      "hi": "उत्तरदायी व्यक्ति / प्रभारी",
      "km": "អ្នកទទួលខុសត្រូវ / អ្នកគ្រប់គ្រង",
      "lo": "ຜູ້ຮັບຜິດຊອບ / ຜູ້ດູແລ",
      "ne": "उत्तरदायी व्यक्ति / प्रभारी"
    },
    "pos": "noun"
  },
  {
    "id": "lv89-06",
    "jp": { "orth": "役職", "reading": "やくしょく" },
    "defs": {
      "en": "position / post / official title",
      "zh": "职务 / 职位 / 职称",
      "ko": "직책 / 직위",
      "vi": "chức vụ / vị trí",
      "es": "cargo / puesto / posición",
      "fr": "poste / fonction / titre officiel",
      "de": "Position / Amt / Dienststellung",
      "it": "posizione / incarico / titolo ufficiale",
      "pt": "cargo / função / posto",
      "id": "jabatan / posisi",
      "tl": "posisyon / tungkulin / title",
      "th": "ตำแหน่ง / ตำแหน่งหน้าที่",
      "ru": "должность / пост / ранг",
      "hi": "पद / पदवी / पदनाम",
      "km": "តួនាទី / មុខតំណែង / តំណែងការងារ",
      "lo": "ຕຳແໜ່ງ / ຕຳແໜ່ງການງານ",
      "ne": "पद / पदनाम / पदस्थिति"
    },
    "pos": "noun"
  },
  {
    "id": "lv89-07",
    "jp": { "orth": "部署", "reading": "ぶしょ" },
    "defs": {
      "en": "department / section / division (in a company)",
      "zh": "部门 / 科室 / 处",
      "ko": "부서 / 부문",
      "vi": "bộ phận / phòng ban / đơn vị",
      "es": "departamento / sección / división",
      "fr": "département / section / service",
      "de": "Abteilung / Bereich / Sektion",
      "it": "reparto / dipartimento / sezione",
      "pt": "departamento / setor / divisão",
      "id": "departemen / divisi / bagian",
      "tl": "departamento / section / division",
      "th": "แผนก / ฝ่าย / หน่วยงาน",
      "ru": "отдел / подразделение / департамент",
      "hi": "विभाग / शाखा / इकाई",
      "km": "ផ្នែក / នាយកដ្ឋាន",
      "lo": "ພະແນກ / ຫ້ອງການ",
      "ne": "विभाग / शाखा / डिभिजन"
    },
    "pos": "noun"
  },
  {
    "id": "lv89-08",
    "jp": { "orth": "文化", "reading": "ぶんか" },
    "defs": {
      "en": "culture / civilization / customs",
      "zh": "文化 / 文明 / 风俗",
      "ko": "문화 / 문명 / 풍속",
      "vi": "văn hóa / nền văn minh / phong tục",
      "es": "cultura / civilización / costumbres",
      "fr": "culture / civilisation / coutumes",
      "de": "Kultur / Zivilisation / Bräuche",
      "it": "cultura / civiltà / usanze",
      "pt": "cultura / civilização / costumes",
      "id": "budaya / peradaban / kebiasaan",
      "tl": "kultura / sibilisasyon / kaugalian",
      "th": "วัฒนธรรม / อารยธรรม / ประเพณี",
      "ru": "культура / цивилизация / обычаи",
      "hi": "संस्कृति / सभ्यता / परंपरा",
      "km": "វប្បធម៌ / អរិយធម៌ / ទម្លាប់",
      "lo": "ວັດທະນະທໍາ / ອາຣະຍະທຳ / ປະເພນີ",
      "ne": "संस्कृति / सभ्यता / चलन"
    },
    "pos": "noun"
  },
  {
    "id": "lv89-09",
    "jp": { "orth": "伝統", "reading": "でんとう" },
    "defs": {
      "en": "tradition / heritage / custom",
      "zh": "传统 / 遗产 / 习俗",
      "ko": "전통 / 관습 / 유산",
      "vi": "truyền thống / di sản / tập tục",
      "es": "tradición / herencia / costumbre",
      "fr": "tradition / héritage / coutume",
      "de": "Tradition / Erbe / Brauch",
      "it": "tradizione / patrimonio / usanza",
      "pt": "tradição / herança / costume",
      "id": "tradisi / warisan / kebiasaan",
      "tl": "tradisyon / heritage / kaugalian",
      "th": "ประเพณี / มรดก / ขนบธรรมเนียม",
      "ru": "традиция / наследие / обычай",
      "hi": "परंपरा / विरासत / रिवाज",
      "km": "ប្រពៃណី / មរតក / ទម្លាប់",
      "lo": "ປະເພນີ / ມໍຣະດົກ / ຂະນົບທໍານຽມ",
      "ne": "परम्परा / संस्कृति / रीतिरिवाज"
    },
    "pos": "noun"
  },
  {
    "id": "lv89-10",
    "jp": { "orth": "習慣", "reading": "しゅうかん" },
    "defs": {
      "en": "habit / custom / practice",
      "zh": "习惯 / 风俗 / 惯例",
      "ko": "습관 / 관습 / 풍습",
      "vi": "thói quen / phong tục / tập quán",
      "es": "costumbre / hábito / práctica",
      "fr": "habitude / coutume / pratique",
      "de": "Gewohnheit / Brauch / Sitte",
      "it": "abitudine / costume / usanza",
      "pt": "hábito / costume / prática",
      "id": "kebiasaan / adat / praktik",
      "tl": "nakasanayan / kaugalian / gawi",
      "th": "นิสัย / ประเพณี / ขนบธรรมเนียม",
      "ru": "привычка / обычай / традиция",
      "hi": "आदत / रिवाज / प्रथा",
      "km": "ទម្លាប់ / ទង្វើជាញឹកញាប់",
      "lo": "ນິໄສ / ປະເພນີ / ຂະນົບທໍານຽມ",
      "ne": "बानी / चलन / प्रथा"
    },
    "pos": "noun"
  }
]
