[
  {
    "id": "lv32-01",
    "jp": { "orth": "フライパン", "reading": "ふらいぱん" },
    "defs": {
      "en": "frying pan / skillet",
      "zh": "平底锅 / 煎锅",
      "ko": "프라이팬 / 후라이팬",
      "vi": "chảo rán",
      "es": "sartén / freidora",
      "fr": "poêle / poêle à frire",
      "de": "Bratpfanne / Pfanne",
      "it": "padella / tegame",
      "pt": "frigideira / panela rasa",
      "id": "wajan / penggorengan",
      "tl": "kawali / frying pan",
      "th": "กระทะ / กระทะทอด",
      "ru": "сковорода",
      "hi": "तलने की कड़ाही / फ्राइंग पैन",
      "km": "ខ្ទះចៀន / ខ្ទះចៀនសាច់",
      "lo": "ກະທະທອດ",
      "ne": "तल्ने प्यान / कराही"
    },
    "pos": "noun"
  },
  {
    "id": "lv32-02",
    "jp": { "orth": "まな板", "reading": "まないた" },
    "defs": {
      "en": "cutting board / chopping board",
      "zh": "砧板 / 切菜板",
      "ko": "도마",
      "vi": "thớt",
      "es": "tabla de cortar / tabla de picar",
      "fr": "planche à découper",
      "de": "Schneidebrett",
      "it": "tagliere",
      "pt": "tábua de cortar",
      "id": "papan potong / talenan",
      "tl": "sangag / chopping board",
      "th": "เขียง",
      "ru": "разделочная доска",
      "hi": "काटने की तख्ती / चॉपिंग बोर्ड",
      "km": "ក្អមកាត់ / ក្អមកាត់សាច់",
      "lo": "ໄມ້ຕັດ / ກະດານຕັດ",
      "ne": "काट्ने पाटी / थाल"
    },
    "pos": "noun"
  },
  {
    "id": "lv32-03",
    "jp": { "orth": "包丁", "reading": "ほうちょう" },
    "defs": {
      "en": "kitchen knife / chef’s knife",
      "zh": "菜刀 / 厨刀",
      "ko": "식칼 / 부엌칼",
      "vi": "dao bếp",
      "es": "cuchillo de cocina",
      "fr": "couteau de cuisine",
      "de": "Küchenmesser / Kochmesser",
      "it": "coltello da cucina",
      "pt": "faca de cozinha",
      "id": "pisau dapur",
      "tl": "kutsilyo sa kusina",
      "th": "มีดทำครัว",
      "ru": "кухонный нож",
      "hi": "रसोई का चाकू",
      "km": "កាំបិតផ្ទះបាយ",
      "lo": "ມີດຄົວ",
      "ne": "रसोई चक्कु / भान्से चक्कु"
    },
    "pos": "noun"
  },
  {
    "id": "lv32-04",
    "jp": { "orth": "冷凍庫", "reading": "れいとうこ" },
    "defs": {
      "en": "freezer / deep-freeze",
      "zh": "冰柜 / 冷冻库",
      "ko": "냉동고",
      "vi": "tủ đông / ngăn đá",
      "es": "congelador / cámara frigorífica",
      "fr": "congélateur / chambre froide",
      "de": "Gefrierschrank / Tiefkühltruhe",
      "it": "congelatore / freezer",
      "pt": "freezer / congelador",
      "id": "lemari pembeku / freezer",
      "tl": "freezer / aparador ng yelo",
      "th": "ช่องแช่แข็ง / ตู้แช่แข็ง",
      "ru": "морозильник / камера",
      "hi": "फ्रीज़र / ठंडा रखने का डिब्बा",
      "km": "ទូរទឹកកក / ប្រអប់ត្រជាក់",
      "lo": "ຕູ້ແຊ່ແຂງ",
      "ne": "फ्रिजको फ्रीजर / शीतगृह"
    },
    "pos": "noun"
  },
  {
    "id": "lv32-05",
    "jp": { "orth": "炊飯器", "reading": "すいはんき" },
    "defs": {
      "en": "rice cooker",
      "zh": "电饭锅 / 煮饭机",
      "ko": "전기밥솥",
      "vi": "nồi cơm điện",
      "es": "olla arrocera / cocedor de arroz",
      "fr": "cuiseur à riz / autocuiseur",
      "de": "Reiskocher",
      "it": "cuociriso / pentola elettrica",
      "pt": "panela elétrica de arroz",
      "id": "penanak nasi / rice cooker",
      "tl": "rice cooker / palayok na kuryente",
      "th": "หม้อหุงข้าวไฟฟ้า",
      "ru": "рисоварка",
      "hi": "चावल पकाने की मशीन / राइस कुकर",
      "km": "ម៉ាស៊ីនចម្អិនអង្ករ",
      "lo": "ໝໍ້ຫຸງເຂົ້າໄຟຟ້າ",
      "ne": "भात पकाउने मेसिन / राइस कुकर"
    },
    "pos": "noun"
  },
  {
    "id": "lv32-06",
    "jp": { "orth": "電子レンジ", "reading": "でんしれんじ" },
    "defs": {
      "en": "microwave oven",
      "zh": "微波炉",
      "ko": "전자레인지",
      "vi": "lò vi sóng",
      "es": "microondas",
      "fr": "four à micro-ondes",
      "de": "Mikrowelle",
      "it": "forno a microonde",
      "pt": "micro-ondas",
      "id": "oven microwave",
      "tl": "microwave / oven",
      "th": "ไมโครเวฟ",
      "ru": "микроволновка",
      "hi": "माइक्रोवेव ओवन",
      "km": "ឡមីក្រូរូវ៉េវ",
      "lo": "ເຕົາໄມໂຄຣເວບ",
      "ne": "माइक्रोवेभ"
    },
    "pos": "noun"
  },
  {
    "id": "lv32-07",
    "jp": { "orth": "トースター", "reading": "とーすたー" },
    "defs": {
      "en": "toaster",
      "zh": "烤面包机",
      "ko": "토스터 / 토스트기",
      "vi": "máy nướng bánh mì",
      "es": "tostadora",
      "fr": "grille-pain",
      "de": "Toaster",
      "it": "tostapane",
      "pt": "torradeira",
      "id": "pemanggang roti / toaster",
      "tl": "tostador / toaster",
      "th": "เครื่องปิ้งขนมปัง",
      "ru": "тостер",
      "hi": "टोस्टर",
      "km": "ម៉ាស៊ីនដុតនំ / តូស្ទ័រ",
      "lo": "ເຄື່ອງປິ້ງຂົ້ວ",
      "ne": "टोस्टर / रोटी सेक्ने मेसिन"
    },
    "pos": "noun"
  },
  {
    "id": "lv32-08",
    "jp": { "orth": "ポット", "reading": "ぽっと" },
    "defs": {
      "en": "pot / kettle / thermos",
      "zh": "壶 / 热水瓶",
      "ko": "포트 / 주전자",
      "vi": "ấm nước / bình giữ nhiệt",
      "es": "tetera / termo",
      "fr": "bouilloire / pot / thermos",
      "de": "Kanne / Wasserkocher / Thermoskanne",
      "it": "bollitore / teiera / thermos",
      "pt": "bule / chaleira / garrafa térmica",
      "id": "teko / termos / ketel",
      "tl": "takure / thermos",
      "th": "กาน้ำ / กระติกน้ำร้อน",
      "ru": "чайник / термос / кувшин",
      "hi": "केतली / थर्मस",
      "km": "កាណែន / បូមទឹកក្តៅ",
      "lo": "ການ້ຳ / ກະຕິກນ້ຳຮ້ອນ",
      "ne": "केतली / थर्मस"
    },
    "pos": "noun"
  },
  {
    "id": "lv32-09",
    "jp": { "orth": "ストロー", "reading": "すとろー" },
    "defs": {
      "en": "straw (drinking straw)",
      "zh": "吸管",
      "ko": "빨대",
      "vi": "ống hút",
      "es": "pajita / popote / sorbete",
      "fr": "paille (pour boire)",
      "de": "Strohhalm / Trinkhalm",
      "it": "cannuccia",
      "pt": "canudo / palhinha",
      "id": "sedotan",
      "tl": "dayami / straw",
      "th": "หลอดดูดน้ำ",
      "ru": "трубочка / соломинка",
      "hi": "स्ट्रॉ / नली",
      "km": "បំពង់បឺតទឹក",
      "lo": "ຫຼອດດູດນ້ຳ",
      "ne": "स्ट्र / पिउने नली"
    },
    "pos": "noun"
  },
  {
    "id": "lv32-10",
    "jp": { "orth": "ティッシュ", "reading": "てぃっしゅ" },
    "defs": {
      "en": "tissue / facial tissue / Kleenex",
      "zh": "纸巾 / 面纸",
      "ko": "휴지 / 티슈",
      "vi": "giấy lau / khăn giấy",
      "es": "pañuelo / papel tisú",
      "fr": "mouchoir / papier essuie-tout",
      "de": "Taschentuch / Papiertaschentuch",
      "it": "fazzoletto di carta / tessuto",
      "pt": "lenço de papel / papel higiênico facial",
      "id": "tisu / tisu wajah",
      "tl": "tisyu / papel na pamunas",
      "th": "กระดาษทิชชู / กระดาษเช็ดหน้า",
      "ru": "салфетка / бумажная ткань",
      "hi": "टिश्यू / कागज़ का रूमाल",
      "km": "ក្រដាសជូត / ក្រដាសសប្បន់",
      "lo": "ກະດາດຊູ / ກະດາດເຊັດໜ້າ",
      "ne": "टिस्यु / कागजी रुमाल"
    },
    "pos": "noun"
  }
]
